fsfind.py
fsfind-0.1.dev0.dist-info/DESCRIPTION.rst
fsfind-0.1.dev0.dist-info/METADATA
fsfind-0.1.dev0.dist-info/RECORD
fsfind-0.1.dev0.dist-info/WHEEL
fsfind-0.1.dev0.dist-info/metadata.json
fsfind-0.1.dev0.dist-info/top_level.txt
